kaizen/__init__.py
kaizen/__main__.py
kaizen/autofix/README_preserve_changes.md
kaizen/autofix/__init__.py
kaizen/autofix/config.yaml
kaizen/autofix/main.py
kaizen/autofix/types.py
kaizen/autofix/code/__init__.py
kaizen/autofix/code/fixer.py
kaizen/autofix/code/llm_fixer.py
kaizen/autofix/file/__init__.py
kaizen/autofix/file/dependency.py
kaizen/autofix/pr/__init__.py
kaizen/autofix/pr/manager.py
kaizen/autofix/test/README_simple_imports.md
kaizen/autofix/test/README_typescript_support.md
kaizen/autofix/test/__init__.py
kaizen/autofix/test/code_region.py
kaizen/autofix/test/enhanced_code_region.py
kaizen/autofix/test/input_parser.py
kaizen/autofix/test/logger.py
kaizen/autofix/test/runner.py
kaizen/autofix/test/test_case.py
kaizen/autofix/test/variable_tracker.py
kaizen/autofix/test/docs/coroutine_reuse_issue_resolution.md
kaizen/autofix/test/docs/flexible_evaluation_guide.md
kaizen/autofix/test/docs/llamaindex_agent_execution.md
kaizen/autofix/test/docs/typescript_timeout_debugging.md
kaizen/cli/__init__.py
kaizen/cli/cli.py
kaizen/cli/commands/README_memory_system.md
kaizen/cli/commands/__init__.py
kaizen/cli/commands/augment.py
kaizen/cli/commands/config.py
kaizen/cli/commands/config_loader.py
kaizen/cli/commands/config_parser.py
kaizen/cli/commands/config_validator.py
kaizen/cli/commands/dependency_manager.py
kaizen/cli/commands/errors.py
kaizen/cli/commands/formatters.py
kaizen/cli/commands/memory.py
kaizen/cli/commands/memory_example.py
kaizen/cli/commands/memory_inspector.py
kaizen/cli/commands/models.py
kaizen/cli/commands/report_writer.py
kaizen/cli/commands/result.py
kaizen/cli/commands/setup.py
kaizen/cli/commands/test.py
kaizen/cli/commands/test_commands.py
kaizen/cli/commands/test_config_memory_integration.py
kaizen/cli/commands/test_enhanced_memory_logging.py
kaizen/cli/commands/test_memory_system.py
kaizen/cli/commands/types.py
kaizen/cli/commands/validation.py
kaizen/cli/commands/.pytest_cache/README.md
kaizen_agent-0.1.9.dist-info/licenses/LICENSE
kaizen_agent-0.1.9.dist-info/METADATA
kaizen_agent-0.1.9.dist-info/WHEEL
kaizen_agent-0.1.9.dist-info/entry_points.txt
kaizen_agent-0.1.9.dist-info/top_level.txt
kaizen_agent-0.1.9.dist-info/RECORD
