Metadata-Version: 2.4
Name: kaizen-agent
Version: 0.1.9
Summary: An AI debugging engineer that continuously tests, analyzes, and improves your AI agents and LLM applications
Author: Yuto Suzuki
Author-email: Your Name <your.email@example.com>
License-Expression: MIT
Classifier: Development Status :: 4 - Beta
Classifier: Intended Audience :: Developers
Classifier: Programming Language :: Python :: 3
Classifier: Programming Language :: Python :: 3.8
Classifier: Programming Language :: Python :: 3.9
Classifier: Programming Language :: Python :: 3.10
Classifier: Programming Language :: Python :: 3.11
Classifier: Topic :: Software Development :: Testing
Classifier: Topic :: Software Development :: Quality Assurance
Requires-Python: >=3.8
License-File: LICENSE
Requires-Dist: click>=8.0.0
Requires-Dist: rich>=10.0.0
Requires-Dist: pyyaml>=6.0.0
Requires-Dist: ruamel.yaml>=0.18.0
Requires-Dist: openai>=1.0.0
Requires-Dist: tenacity>=8.0.0
Requires-Dist: pydantic>=1.10.0
Requires-Dist: PyGithub>=1.59.0
Requires-Dist: python-dotenv>=0.19.0
Requires-Dist: google-generativeai>=0.3.2
Provides-Extra: dev
Requires-Dist: black>=23.0.0; extra == "dev"
Requires-Dist: isort>=5.0.0; extra == "dev"
Requires-Dist: mypy>=1.0.0; extra == "dev"
Requires-Dist: pre-commit>=3.0.0; extra == "dev"
Requires-Dist: sphinx>=7.0.0; extra == "dev"
Requires-Dist: sphinx-rtd-theme>=1.0.0; extra == "dev"
Dynamic: author
Dynamic: license-file
Dynamic: requires-python
